payload_validator/__init__.py
payload_validator/error_contexts.py
payload_validator/exceptions.py
payload_validator/validators.py
payload_validator/__pycache__/__init__.cpython-311.pyc
payload_validator/__pycache__/error_contexts.cpython-311.pyc
payload_validator/__pycache__/exceptions.cpython-311.pyc
payload_validator/__pycache__/validators.cpython-311.pyc
tests/__init__.py
tests/test_error_contexts.py
tests/test_exceptions.py
tests/test_validators.py
payload_validator-0.1.11.dist-info/LICENSE
payload_validator-0.1.11.dist-info/METADATA
payload_validator-0.1.11.dist-info/WHEEL
payload_validator-0.1.11.dist-info/top_level.txt
payload_validator-0.1.11.dist-info/RECORD
