Metadata-Version: 2.1
Name: payload-validator
Version: 0.1.11
Summary: Validating payload datas for Python
Home-page: https://github.com/cwadven/payload-validator
Author: cwadven
Author-email: cwadven4@gmail.com
Maintainer: cwadven
License: MIT
Keywords: input,payload,validator,validate,validation,data,datas,python,python3,python3.6,python3.7,python3.8,python3.11
Classifier: Environment :: Web Environment
Classifier: Intended Audience :: Developers
Classifier: License :: OSI Approved :: MIT License
Classifier: Operating System :: OS Independent
Classifier: Programming Language :: Python :: 3
Classifier: Programming Language :: Python :: 3.6
Classifier: Programming Language :: Python :: 3.7
Classifier: Programming Language :: Python :: 3.8
Classifier: Programming Language :: Python :: 3.11
Classifier: Topic :: Software Development :: Libraries :: Python Modules
License-File: LICENSE
